emsutil/__init__.py
emsutil/const.py
emsutil/emdata.py
emsutil/file.py
emsutil/isola.py
emsutil/lib.py
emsutil/material.py
emsutil/rogers.py
emsutil/themes.py
emsutil/inexport/ffdata.py
emsutil/inexport/strutil.py
emsutil/plot/__init__.py
emsutil/plot/plot2d.py
emsutil/pyvista/__init__.py
emsutil/pyvista/cmap_maker.py
emsutil/pyvista/display.py
emsutil/pyvista/display_settings.py
emsutil/pyvista/utils.py
emsutil/pyvista/textures/background.png
emsutil/pyvista/textures/tex1.png
emsutil/pyvista/textures/tex2.png
emsutil/pyvista/textures/tex3.png
emsutil/pyvista/textures/tex4.png
emsutil/pyvista/textures/tex5.png
emsutil/pyvista/textures/tex6.png
emsutil-0.4.0.dist-info/METADATA
emsutil-0.4.0.dist-info/WHEEL
emsutil-0.4.0.dist-info/RECORD
