Metadata-Version: 2.4
Name: emsutil
Version: 0.4.0
Summary: Common utilities for Emerge projects EMerge, Optycal and Heavi
Project-URL: Homepage, https://github.com/FennisRobert/emsutil
Project-URL: Issues, https://github.com/FennisRobert/emsutil/issues
Requires-Python: >=3.10
Requires-Dist: loguru>=0.7.3
Requires-Dist: matplotlib>=3.8.0
Requires-Dist: msgpack-numpy>=0.4.8
Requires-Dist: msgpack>=1.1.2
Requires-Dist: numpy<2.3,>=1.24
Requires-Dist: pyvista>=0.46.4
Requires-Dist: scipy>=1.14.0
